README.md
setup.cfg
setup.py
slurm_handler/__init__.py
slurm_handler/slurm_handler.py
slurm_handler.egg-info/PKG-INFO
slurm_handler.egg-info/SOURCES.txt
slurm_handler.egg-info/dependency_links.txt
slurm_handler.egg-info/top_level.txt