Metadata-Version: 1.1
Name: slurm-handler
Version: 0.0.16
Summary: job submission in python using the slurm job manager
Home-page: https://github.com/YSanchezAraujo/slurm_handler
Author: Yoel Sanchez Araujo
Author-email: yoelsanchez006@gmail.com
License: UNKNOWN
Download-URL: https://github.com/YSanchezAraujo/archive/0.0.16.tar.gz
Keywords: clusters,slurm
Platform: UNKNOWN
